NiukeDianqigongchengshiQiuzhiJingyanFenxiang20212022/README.md
NiukeDianqigongchengshiQiuzhiJingyanFenxiang20212022/__init__.py
NiukeDianqigongchengshiQiuzhiJingyanFenxiang20212022/__main__.py
NiukeDianqigongchengshiQiuzhiJingyanFenxiang20212022/file.epub
NiukeDianqigongchengshiQiuzhiJingyanFenxiang20212022/index.html
NiukeDianqigongchengshiQiuzhiJingyanFenxiang20212022/css/__init__.py
NiukeDianqigongchengshiQiuzhiJingyanFenxiang20212022/css/annotations.css
NiukeDianqigongchengshiQiuzhiJingyanFenxiang20212022/css/main.css
NiukeDianqigongchengshiQiuzhiJingyanFenxiang20212022/css/normalize.css
NiukeDianqigongchengshiQiuzhiJingyanFenxiang20212022/css/popup.css
NiukeDianqigongchengshiQiuzhiJingyanFenxiang20212022/font/__init__.py
NiukeDianqigongchengshiQiuzhiJingyanFenxiang20212022/font/fontello.eot
NiukeDianqigongchengshiQiuzhiJingyanFenxiang20212022/font/fontello.svg
NiukeDianqigongchengshiQiuzhiJingyanFenxiang20212022/font/fontello.ttf
NiukeDianqigongchengshiQiuzhiJingyanFenxiang20212022/font/fontello.woff
NiukeDianqigongchengshiQiuzhiJingyanFenxiang20212022/img/__init__.py
NiukeDianqigongchengshiQiuzhiJingyanFenxiang20212022/img/annotator-glyph-sprite.png
NiukeDianqigongchengshiQiuzhiJingyanFenxiang20212022/img/annotator-icon-sprite.png
NiukeDianqigongchengshiQiuzhiJingyanFenxiang20212022/img/apple-touch-icon.png
NiukeDianqigongchengshiQiuzhiJingyanFenxiang20212022/img/cancelfullscreen.png
NiukeDianqigongchengshiQiuzhiJingyanFenxiang20212022/img/close.png
NiukeDianqigongchengshiQiuzhiJingyanFenxiang20212022/img/fullscreen.png
NiukeDianqigongchengshiQiuzhiJingyanFenxiang20212022/img/loader.gif
NiukeDianqigongchengshiQiuzhiJingyanFenxiang20212022/img/menu-icon.png
NiukeDianqigongchengshiQiuzhiJingyanFenxiang20212022/img/save.png
NiukeDianqigongchengshiQiuzhiJingyanFenxiang20212022/img/saved.png
NiukeDianqigongchengshiQiuzhiJingyanFenxiang20212022/img/settings-s.png
NiukeDianqigongchengshiQiuzhiJingyanFenxiang20212022/img/settings.png
niuke_dianqigongchengshi_qiuzhi_jingyan_fenxiang_2021_2022-2024.3.6.0.dist-info/METADATA
niuke_dianqigongchengshi_qiuzhi_jingyan_fenxiang_2021_2022-2024.3.6.0.dist-info/WHEEL
niuke_dianqigongchengshi_qiuzhi_jingyan_fenxiang_2021_2022-2024.3.6.0.dist-info/entry_points.txt
niuke_dianqigongchengshi_qiuzhi_jingyan_fenxiang_2021_2022-2024.3.6.0.dist-info/top_level.txt
niuke_dianqigongchengshi_qiuzhi_jingyan_fenxiang_2021_2022-2024.3.6.0.dist-info/RECORD
